python_qweather/__init__.py
python_qweather/const.py
python_qweather/qweather.py
python_qweather-0.1.4.dist-info/LICENSE
python_qweather-0.1.4.dist-info/WHEEL
python_qweather-0.1.4.dist-info/METADATA
python_qweather-0.1.4.dist-info/RECORD
