Metadata-Version: 2.1
Name: python-qweather
Version: 0.1.4
Summary: Python API wrapper for https://qweather.com
Home-page: https://github.com/dofine/python-qweather
License: MIT
Keywords: weather
Author: dofine
Author-email: dofine@users.noreply.github.com
Requires-Python: >=3.7,<4.0
Classifier: License :: OSI Approved :: MIT License
Classifier: Programming Language :: Python
Classifier: Programming Language :: Python :: 3
Classifier: Programming Language :: Python :: 3.10
Classifier: Programming Language :: Python :: 3.7
Classifier: Programming Language :: Python :: 3.8
Classifier: Programming Language :: Python :: 3.9
Requires-Dist: pytest-asyncio (>=0.18.3,<0.19.0)
Project-URL: Repository, https://github.com/dofine/python-qweather
